sovon_cms/__init__.py
sovon_cms/main.py
sovon_cms/version.py
sovon_cms-0.1.0.dist-info/LICENSE
sovon_cms-0.1.0.dist-info/LICENSE.txt
sovon_cms-0.1.0.dist-info/METADATA
sovon_cms-0.1.0.dist-info/WHEEL
sovon_cms-0.1.0.dist-info/entry_points.txt
sovon_cms-0.1.0.dist-info/top_level.txt
sovon_cms-0.1.0.dist-info/RECORD
